[
  {
    "tile_id": "tile_x00000_y00000",
    "rubin_band": "rubin_r",
    "matches": 114,
    "raw_median_mas": 45.5124397277832,
    "pred_median_mas": 35.62335968017578,
    "sigma_median_mas": 21.021289825439453,
    "grid_shape": [
      7,
      8
    ],
    "anchor_radius_px": 325.0
  },
  {
    "tile_id": "tile_x00000_y00768",
    "rubin_band": "rubin_r",
    "matches": 101,
    "raw_median_mas": 52.39455032348633,
    "pred_median_mas": 33.27946853637695,
    "sigma_median_mas": 25.766559600830078,
    "grid_shape": [
      7,
      7
    ],
    "anchor_radius_px": 350.0
  },
  {
    "tile_id": "tile_x00000_y01024",
    "rubin_band": "rubin_r",
    "matches": 98,
    "raw_median_mas": 47.23741912841797,
    "pred_median_mas": 31.82297134399414,
    "sigma_median_mas": 25.391000747680664,
    "grid_shape": [
      7,
      7
    ],
    "anchor_radius_px": 350.0
  },
  {
    "tile_id": "tile_x00000_y02560",
    "rubin_band": "rubin_r",
    "matches": 127,
    "raw_median_mas": 52.408329010009766,
    "pred_median_mas": 37.281856536865234,
    "sigma_median_mas": 22.718278884887695,
    "grid_shape": [
      7,
      8
    ],
    "anchor_radius_px": 325.0
  },
  {
    "tile_id": "tile_x00256_y01024",
    "rubin_band": "rubin_r",
    "matches": 83,
    "raw_median_mas": 46.78432083129883,
    "pred_median_mas": 34.011474609375,
    "sigma_median_mas": 23.882658004760742,
    "grid_shape": [
      6,
      6
    ],
    "anchor_radius_px": 420.0
  },
  {
    "tile_id": "tile_x00256_y01280",
    "rubin_band": "rubin_r",
    "matches": 90,
    "raw_median_mas": 55.6363525390625,
    "pred_median_mas": 39.495094299316406,
    "sigma_median_mas": 23.098215103149414,
    "grid_shape": [
      6,
      7
    ],
    "anchor_radius_px": 385.0
  },
  {
    "tile_id": "tile_x00256_y02304",
    "rubin_band": "rubin_r",
    "matches": 108,
    "raw_median_mas": 51.89031982421875,
    "pred_median_mas": 36.03053283691406,
    "sigma_median_mas": 21.270885467529297,
    "grid_shape": [
      7,
      7
    ],
    "anchor_radius_px": 350.0
  },
  {
    "tile_id": "tile_x00512_y01024",
    "rubin_band": "rubin_r",
    "matches": 102,
    "raw_median_mas": 53.14122772216797,
    "pred_median_mas": 34.28499221801758,
    "sigma_median_mas": 29.680076599121094,
    "grid_shape": [
      7,
      7
    ],
    "anchor_radius_px": 350.0
  },
  {
    "tile_id": "tile_x00512_y01280",
    "rubin_band": "rubin_r",
    "matches": 93,
    "raw_median_mas": 65.51123046875,
    "pred_median_mas": 42.932090759277344,
    "sigma_median_mas": 21.891569137573242,
    "grid_shape": [
      6,
      7
    ],
    "anchor_radius_px": 385.0
  },
  {
    "tile_id": "tile_x00512_y02048",
    "rubin_band": "rubin_r",
    "matches": 93,
    "raw_median_mas": 40.92711639404297,
    "pred_median_mas": 29.54912567138672,
    "sigma_median_mas": 21.05087661743164,
    "grid_shape": [
      6,
      7
    ],
    "anchor_radius_px": 385.0
  },
  {
    "tile_id": "tile_x00512_y02304",
    "rubin_band": "rubin_r",
    "matches": 91,
    "raw_median_mas": 52.805885314941406,
    "pred_median_mas": 38.142250061035156,
    "sigma_median_mas": 21.143108367919922,
    "grid_shape": [
      6,
      7
    ],
    "anchor_radius_px": 385.0
  },
  {
    "tile_id": "tile_x00768_y00000",
    "rubin_band": "rubin_r",
    "matches": 99,
    "raw_median_mas": 49.19367218017578,
    "pred_median_mas": 37.627281188964844,
    "sigma_median_mas": 29.002954483032227,
    "grid_shape": [
      7,
      7
    ],
    "anchor_radius_px": 350.0
  },
  {
    "tile_id": "tile_x00768_y01024",
    "rubin_band": "rubin_r",
    "matches": 104,
    "raw_median_mas": 45.86863708496094,
    "pred_median_mas": 28.86188507080078,
    "sigma_median_mas": 21.514787673950195,
    "grid_shape": [
      7,
      7
    ],
    "anchor_radius_px": 350.0
  },
  {
    "tile_id": "tile_x00768_y01280",
    "rubin_band": "rubin_r",
    "matches": 94,
    "raw_median_mas": 64.9385986328125,
    "pred_median_mas": 38.883296966552734,
    "sigma_median_mas": 21.427053451538086,
    "grid_shape": [
      6,
      7
    ],
    "anchor_radius_px": 385.0
  },
  {
    "tile_id": "tile_x00768_y02048",
    "rubin_band": "rubin_r",
    "matches": 75,
    "raw_median_mas": 32.52722930908203,
    "pred_median_mas": 29.443056106567383,
    "sigma_median_mas": 20.22723388671875,
    "grid_shape": [
      6,
      6
    ],
    "anchor_radius_px": 420.0
  },
  {
    "tile_id": "tile_x01024_y00000",
    "rubin_band": "rubin_r",
    "matches": 110,
    "raw_median_mas": 50.74807357788086,
    "pred_median_mas": 32.50407028198242,
    "sigma_median_mas": 33.26755905151367,
    "grid_shape": [
      7,
      7
    ],
    "anchor_radius_px": 350.0
  },
  {
    "tile_id": "tile_x01280_y00256",
    "rubin_band": "rubin_r",
    "matches": 108,
    "raw_median_mas": 50.746925354003906,
    "pred_median_mas": 32.557186126708984,
    "sigma_median_mas": 28.67519760131836,
    "grid_shape": [
      7,
      7
    ],
    "anchor_radius_px": 350.0
  },
  {
    "tile_id": "tile_x01280_y00512",
    "rubin_band": "rubin_r",
    "matches": 124,
    "raw_median_mas": 52.032283782958984,
    "pred_median_mas": 29.979726791381836,
    "sigma_median_mas": 24.995424270629883,
    "grid_shape": [
      7,
      8
    ],
    "anchor_radius_px": 325.0
  },
  {
    "tile_id": "tile_x01280_y00768",
    "rubin_band": "rubin_r",
    "matches": 136,
    "raw_median_mas": 48.84177780151367,
    "pred_median_mas": 31.419429779052734,
    "sigma_median_mas": 29.20963478088379,
    "grid_shape": [
      8,
      8
    ],
    "anchor_radius_px": 300.0
  },
  {
    "tile_id": "tile_x01280_y01024",
    "rubin_band": "rubin_r",
    "matches": 121,
    "raw_median_mas": 48.49034881591797,
    "pred_median_mas": 33.23863220214844,
    "sigma_median_mas": 28.167036056518555,
    "grid_shape": [
      7,
      8
    ],
    "anchor_radius_px": 325.0
  },
  {
    "tile_id": "tile_x01280_y02560",
    "rubin_band": "rubin_r",
    "matches": 85,
    "raw_median_mas": 46.56513595581055,
    "pred_median_mas": 35.9600715637207,
    "sigma_median_mas": 23.398908615112305,
    "grid_shape": [
      6,
      7
    ],
    "anchor_radius_px": 385.0
  },
  {
    "tile_id": "tile_x01536_y00512",
    "rubin_band": "rubin_r",
    "matches": 117,
    "raw_median_mas": 46.577457427978516,
    "pred_median_mas": 32.588966369628906,
    "sigma_median_mas": 24.974733352661133,
    "grid_shape": [
      7,
      8
    ],
    "anchor_radius_px": 325.0
  },
  {
    "tile_id": "tile_x01536_y00768",
    "rubin_band": "rubin_r",
    "matches": 132,
    "raw_median_mas": 48.49562454223633,
    "pred_median_mas": 27.921072006225586,
    "sigma_median_mas": 32.57643508911133,
    "grid_shape": [
      8,
      8
    ],
    "anchor_radius_px": 300.0
  },
  {
    "tile_id": "tile_x01536_y01536",
    "rubin_band": "rubin_r",
    "matches": 111,
    "raw_median_mas": 57.48163986206055,
    "pred_median_mas": 35.683956146240234,
    "sigma_median_mas": 27.17848777770996,
    "grid_shape": [
      7,
      7
    ],
    "anchor_radius_px": 350.0
  },
  {
    "tile_id": "tile_x01536_y01792",
    "rubin_band": "rubin_r",
    "matches": 106,
    "raw_median_mas": 50.77875518798828,
    "pred_median_mas": 35.24293518066406,
    "sigma_median_mas": 20.3819580078125,
    "grid_shape": [
      7,
      7
    ],
    "anchor_radius_px": 350.0
  },
  {
    "tile_id": "tile_x01792_y00512",
    "rubin_band": "rubin_r",
    "matches": 92,
    "raw_median_mas": 45.932899475097656,
    "pred_median_mas": 29.106815338134766,
    "sigma_median_mas": 26.955089569091797,
    "grid_shape": [
      6,
      7
    ],
    "anchor_radius_px": 385.0
  },
  {
    "tile_id": "tile_x01792_y00768",
    "rubin_band": "rubin_r",
    "matches": 105,
    "raw_median_mas": 42.35443878173828,
    "pred_median_mas": 21.28894805908203,
    "sigma_median_mas": 33.80223083496094,
    "grid_shape": [
      7,
      7
    ],
    "anchor_radius_px": 350.0
  },
  {
    "tile_id": "tile_x01792_y01536",
    "rubin_band": "rubin_r",
    "matches": 121,
    "raw_median_mas": 53.33706283569336,
    "pred_median_mas": 31.551149368286133,
    "sigma_median_mas": 30.845399856567383,
    "grid_shape": [
      7,
      8
    ],
    "anchor_radius_px": 325.0
  },
  {
    "tile_id": "tile_x01792_y01792",
    "rubin_band": "rubin_r",
    "matches": 98,
    "raw_median_mas": 46.71858215332031,
    "pred_median_mas": 33.11658477783203,
    "sigma_median_mas": 20.148117065429688,
    "grid_shape": [
      7,
      7
    ],
    "anchor_radius_px": 350.0
  },
  {
    "tile_id": "tile_x02048_y00512",
    "rubin_band": "rubin_r",
    "matches": 98,
    "raw_median_mas": 55.988521575927734,
    "pred_median_mas": 37.183624267578125,
    "sigma_median_mas": 24.321163177490234,
    "grid_shape": [
      7,
      7
    ],
    "anchor_radius_px": 350.0
  },
  {
    "tile_id": "tile_x02048_y00768",
    "rubin_band": "rubin_r",
    "matches": 109,
    "raw_median_mas": 43.49530792236328,
    "pred_median_mas": 33.69207763671875,
    "sigma_median_mas": 25.121978759765625,
    "grid_shape": [
      7,
      7
    ],
    "anchor_radius_px": 350.0
  },
  {
    "tile_id": "tile_x02048_y01536",
    "rubin_band": "rubin_r",
    "matches": 97,
    "raw_median_mas": 44.46928405761719,
    "pred_median_mas": 35.38666915893555,
    "sigma_median_mas": 22.786846160888672,
    "grid_shape": [
      6,
      7
    ],
    "anchor_radius_px": 385.0
  },
  {
    "tile_id": "tile_x02048_y01792",
    "rubin_band": "rubin_r",
    "matches": 83,
    "raw_median_mas": 45.039554595947266,
    "pred_median_mas": 30.429201126098633,
    "sigma_median_mas": 18.96205711364746,
    "grid_shape": [
      6,
      6
    ],
    "anchor_radius_px": 420.0
  },
  {
    "tile_id": "tile_x02304_y00512",
    "rubin_band": "rubin_r",
    "matches": 91,
    "raw_median_mas": 36.31760787963867,
    "pred_median_mas": 28.865398406982422,
    "sigma_median_mas": 24.06343650817871,
    "grid_shape": [
      6,
      7
    ],
    "anchor_radius_px": 385.0
  },
  {
    "tile_id": "tile_x02304_y00768",
    "rubin_band": "rubin_r",
    "matches": 123,
    "raw_median_mas": 41.3395881652832,
    "pred_median_mas": 34.72329330444336,
    "sigma_median_mas": 24.152549743652344,
    "grid_shape": [
      7,
      8
    ],
    "anchor_radius_px": 325.0
  },
  {
    "tile_id": "tile_x02304_y01024",
    "rubin_band": "rubin_r",
    "matches": 92,
    "raw_median_mas": 45.04228973388672,
    "pred_median_mas": 36.232139587402344,
    "sigma_median_mas": 20.434986114501953,
    "grid_shape": [
      6,
      7
    ],
    "anchor_radius_px": 385.0
  },
  {
    "tile_id": "tile_x02304_y02048",
    "rubin_band": "rubin_r",
    "matches": 62,
    "raw_median_mas": 33.62004852294922,
    "pred_median_mas": 23.649362564086914,
    "sigma_median_mas": 21.919652938842773,
    "grid_shape": [
      5,
      6
    ],
    "anchor_radius_px": 472.5
  },
  {
    "tile_id": "tile_x02304_y02304",
    "rubin_band": "rubin_r",
    "matches": 100,
    "raw_median_mas": 49.205116271972656,
    "pred_median_mas": 30.264892578125,
    "sigma_median_mas": 27.492982864379883,
    "grid_shape": [
      7,
      7
    ],
    "anchor_radius_px": 350.0
  },
  {
    "tile_id": "tile_x02560_y00256",
    "rubin_band": "rubin_r",
    "matches": 43,
    "raw_median_mas": 27.69071388244629,
    "pred_median_mas": 21.216449737548828,
    "sigma_median_mas": 18.439167022705078,
    "grid_shape": [
      4,
      5
    ],
    "anchor_radius_px": 612.5
  },
  {
    "tile_id": "tile_x02560_y00512",
    "rubin_band": "rubin_r",
    "matches": 78,
    "raw_median_mas": 32.53672409057617,
    "pred_median_mas": 22.851287841796875,
    "sigma_median_mas": 24.418081283569336,
    "grid_shape": [
      6,
      6
    ],
    "anchor_radius_px": 420.0
  },
  {
    "tile_id": "tile_x02560_y00768",
    "rubin_band": "rubin_r",
    "matches": 103,
    "raw_median_mas": 39.10176086425781,
    "pred_median_mas": 27.358200073242188,
    "sigma_median_mas": 24.79848861694336,
    "grid_shape": [
      7,
      7
    ],
    "anchor_radius_px": 350.0
  },
  {
    "tile_id": "tile_x02560_y01024",
    "rubin_band": "rubin_r",
    "matches": 108,
    "raw_median_mas": 46.55590057373047,
    "pred_median_mas": 36.36077880859375,
    "sigma_median_mas": 22.147174835205078,
    "grid_shape": [
      7,
      7
    ],
    "anchor_radius_px": 350.0
  },
  {
    "tile_id": "tile_x02560_y01280",
    "rubin_band": "rubin_r",
    "matches": 114,
    "raw_median_mas": 46.027130126953125,
    "pred_median_mas": 35.85663986206055,
    "sigma_median_mas": 21.823217391967773,
    "grid_shape": [
      7,
      8
    ],
    "anchor_radius_px": 325.0
  },
  {
    "tile_id": "tile_x02560_y01536",
    "rubin_band": "rubin_r",
    "matches": 105,
    "raw_median_mas": 40.55488204956055,
    "pred_median_mas": 30.16618537902832,
    "sigma_median_mas": 21.794898986816406,
    "grid_shape": [
      7,
      7
    ],
    "anchor_radius_px": 350.0
  },
  {
    "tile_id": "tile_x02560_y02304",
    "rubin_band": "rubin_r",
    "matches": 126,
    "raw_median_mas": 54.673789978027344,
    "pred_median_mas": 32.963722229003906,
    "sigma_median_mas": 27.696949005126953,
    "grid_shape": [
      7,
      8
    ],
    "anchor_radius_px": 325.0
  },
  {
    "tile_id": "tile_x02560_y02560",
    "rubin_band": "rubin_r",
    "matches": 127,
    "raw_median_mas": 47.184539794921875,
    "pred_median_mas": 33.64767837524414,
    "sigma_median_mas": 27.649118423461914,
    "grid_shape": [
      7,
      8
    ],
    "anchor_radius_px": 325.0
  },
  {
    "tile_id": "tile_x02560_y02816",
    "rubin_band": "rubin_r",
    "matches": 134,
    "raw_median_mas": 48.375003814697266,
    "pred_median_mas": 34.65901184082031,
    "sigma_median_mas": 28.223054885864258,
    "grid_shape": [
      8,
      8
    ],
    "anchor_radius_px": 300.0
  },
  {
    "tile_id": "tile_x02816_y02304",
    "rubin_band": "rubin_r",
    "matches": 110,
    "raw_median_mas": 55.01464080810547,
    "pred_median_mas": 32.64716339111328,
    "sigma_median_mas": 27.107101440429688,
    "grid_shape": [
      7,
      7
    ],
    "anchor_radius_px": 350.0
  }
]